tg_error_logger/__init__.py
tg_error_logger/log.py
tg_error_logger-0.0.1.dist-info/METADATA
tg_error_logger-0.0.1.dist-info/WHEEL
tg_error_logger-0.0.1.dist-info/top_level.txt
tg_error_logger-0.0.1.dist-info/RECORD
