Metadata-Version: 2.2
Name: tg_error_logger
Version: 0.0.1
Summary: Telegram bot loger for django
Author: Bahodir
Author-email: weebcreator94@gmail.com
Requires-Python: >=3.6
Requires-Dist: python-dotenv
Dynamic: author
Dynamic: author-email
Dynamic: requires-dist
Dynamic: requires-python
Dynamic: summary
